ftrack_s3_accessor/__init__.py
ftrack_s3_accessor/s3.py
ftrack_s3_accessor-0.1.7.post1.dist-info/LICENSE.txt
ftrack_s3_accessor-0.1.7.post1.dist-info/WHEEL
ftrack_s3_accessor-0.1.7.post1.dist-info/METADATA
ftrack_s3_accessor-0.1.7.post1.dist-info/RECORD
