Metadata-Version: 2.1
Name: ftrack-s3-accessor
Version: 0.1.7.post1
Summary: A ftrack s3 accessor updated to work with ftrack-python-api and boto3.
Home-page: https://github.com/niftydigits/ftrack-s3-accessor
License: Apache 2
Author: Ian Wootten
Author-email: hi@niftydigits.com
Requires-Python: >=2.7, !=3.0.*, !=3.1.*, !=3.2.*, !=3.3.*, !=3.4.*, !=3.5.*, !=3.6.*
Classifier: License :: Other/Proprietary License
Classifier: Programming Language :: Python :: 2
Classifier: Programming Language :: Python :: 3
Classifier: Programming Language :: Python :: 3.7
Classifier: Programming Language :: Python :: 3.8
Classifier: Programming Language :: Python :: 3.9
Provides-Extra: action
Requires-Dist: boto3 (>=1.15.10,<2.0.0)
Requires-Dist: ftrack-action-handler (>=0.2.1,<0.3.0); extra == "action"
Requires-Dist: ftrack-python-api (>=2.0.0,<3.0.0)
Project-URL: Repository, https://github.com/niftydigits/ftrack-s3-accessor
